<illness name="flu"><age>8</age><date>2009-11-16T14:18:18.309-05:00</date><location type="zip" n="300">20191</location><symptom><type>sore throat</type><when start="1" duration="1"/><severity>2</severity></symptom><symptom><type>aches</type><qualifier>body</qualifier><when start="2" duration="4"/><severity>2</severity></symptom><symptom><type>vomiting</type><when start="2" duration="1"/><severity>2</severity></symptom><symptom><type>tired</type><when start="1" duration="8"/><severity/></symptom><overall-duration>8.33333333333333</overall-duration></illness>
